check_url.py
Check_URL-1.0.6.dist-info/LICENSE
Check_URL-1.0.6.dist-info/METADATA
Check_URL-1.0.6.dist-info/WHEEL
Check_URL-1.0.6.dist-info/top_level.txt
Check_URL-1.0.6.dist-info/RECORD
